setup.cfg
setup.py
ContrailCA.egg-info/PKG-INFO
ContrailCA.egg-info/SOURCES.txt
ContrailCA.egg-info/dependency_links.txt
ContrailCA.egg-info/entry_points.txt
ContrailCA.egg-info/not-zip-safe
ContrailCA.egg-info/requires.txt
ContrailCA.egg-info/top_level.txt
contrail/__init__.py
contrail/security/__init__.py
contrail/security/ca/__init__.py
contrail/security/ca/base.py
contrail/security/ca/callout_impl.py
contrail/security/ca/cert_req.py
contrail/security/ca/impl.py
contrail/security/ca/subj_alt_name.py
contrail/security/ca/test/README
contrail/security/ca/test/__init__.py
contrail/security/ca/test/ca.cfg
contrail/security/ca/test/callout_ca.cfg
contrail/security/ca/test/my.crt
contrail/security/ca/test/my.key
contrail/security/ca/test/my1.crt
contrail/security/ca/test/my1.key
contrail/security/ca/test/myca.crt
contrail/security/ca/test/myca.key
contrail/security/ca/test/test_ca_callout_impl.py
contrail/security/ca/test/test_ca_impl.py
contrail/security/ca/test/test_cli.py
contrail/security/ca/test/ca_config/__init__.py
contrail/security/ca/test/ca_config/index.txt
contrail/security/ca/test/ca_config/myca.crt
contrail/security/ca/test/ca_config/myca.key
contrail/security/ca/test/ca_config/serial
contrail/security/ca/test/ca_config/test-ca.cfg
contrail/security/ca/test/ca_config/newcerts/README
contrail/security/ca/test/ca_config/newcerts/__init__.py
contrail/security/ca/utils/__init__.py
contrail/security/ca/utils/cli.py