Metadata-Version: 1.1
Name: ContrailCA
Version: 0.4.0
Summary: Certificate Authority
Home-page: https://github.com/cedadev/CertificateAuthority
Author: Philip Kershaw
Author-email: Philip.Kershaw@stfc.ac.uk
License: BSD - See LICENSE file in top-level directory
Platform: POSIX
Platform: Linux
Platform: Windows
Classifier: Development Status :: 5 - Production/Stable
Classifier: Environment :: Console
Classifier: Environment :: Web Environment
Classifier: Intended Audience :: End Users/Desktop
Classifier: Intended Audience :: Developers
Classifier: Intended Audience :: System Administrators
Classifier: Intended Audience :: Science/Research
Classifier: License :: OSI Approved :: BSD License
Classifier: Natural Language :: English
Classifier: Operating System :: Microsoft :: Windows
Classifier: Operating System :: POSIX :: Linux
Classifier: Programming Language :: Python
Classifier: Programming Language :: Python :: 3
Classifier: Topic :: Security
Classifier: Topic :: Internet
Classifier: Topic :: Scientific/Engineering
Classifier: Topic :: System :: Distributed Computing
Classifier: Topic :: System :: Systems Administration :: Authentication/Directory
Classifier: Topic :: Software Development :: Libraries :: Python Modules
